setup.py
PyNeon/__init__.py
PyNeon/neongraphics.py
PyNeon/neonutils.py
PyNeon/neonwindow.py
PyNeon.egg-info/PKG-INFO
PyNeon.egg-info/SOURCES.txt
PyNeon.egg-info/dependency_links.txt
PyNeon.egg-info/requires.txt
PyNeon.egg-info/top_level.txt
examples/drawingrect.py
examples/event_handling.py
examples/helloworld.py
examples/loading_textures.py
examples/rect_collision.py