Metadata-Version: 2.1
Name: PyNeon
Version: 0.2.1
Summary: Light weight game development library
Home-page: https://github.com/jakeconner5444
Author: jack ronn
Author-email: jakeronnstudios@gmail.com
